django_giropay/__init__.py
django_giropay/admin.py
django_giropay/constants.py
django_giropay/models.py
django_giropay/settings.py
django_giropay/urls.py
django_giropay/utils.py
django_giropay/views.py
django_giropay/wrappers.py
django_giropay/migrations/0001_initial.py
django_giropay/migrations/__init__.py
django_giropay-1.0.0.dist-info/LICENSE
django_giropay-1.0.0.dist-info/METADATA
django_giropay-1.0.0.dist-info/WHEEL
django_giropay-1.0.0.dist-info/top_level.txt
django_giropay-1.0.0.dist-info/RECORD
